mabfs/__init__.py
mabfs/distributions.py
mabfs/tests.py
mabfs/ts_selector.py
mabfs-0.0.4.dist-info/LICENSE
mabfs-0.0.4.dist-info/METADATA
mabfs-0.0.4.dist-info/WHEEL
mabfs-0.0.4.dist-info/top_level.txt
mabfs-0.0.4.dist-info/RECORD
