Metadata-Version: 2.1
Name: mabfs
Version: 0.0.4
Summary: Multi armed bandit feature selection
Home-page: https://github.com/feodal01/Multi-armed-bandit-feature-selection
Author: Evgeny Orlov
Author-email: evgenyorlov1991@gmail.com
Classifier: Programming Language :: Python :: 3.9
Classifier: License :: OSI Approved :: MIT License
Classifier: Operating System :: OS Independent
Requires-Python: >=3.6
License-File: LICENSE
Requires-Dist: numpy
Requires-Dist: pandas
Requires-Dist: sklearn
Requires-Dist: scipy
Requires-Dist: joblib
Requires-Dist: pyyaml
Requires-Dist: multiprocess
